anodet/__init__.py
anomavision/__init__.py
anomavision/config.py
anomavision/datasets/__init__.py
anomavision/datasets/dataset.py
anomavision/datasets/MQTTSource.py
anomavision/datasets/mvtec_dataset.py
anomavision/datasets/StreamDataset.py
anomavision/datasets/StreamSource.py
anomavision/datasets/StreamSourceFactory.py
anomavision/datasets/TCPsource.py
anomavision/datasets/VideoSource.py
anomavision/datasets/WebcamSource.py
anomavision/feature_extraction.py
anomavision/general.py
anomavision/inference/__init__.py
anomavision/inference/model/__init__.py
anomavision/inference/model/backends/__init__.py
anomavision/inference/model/backends/base.py
anomavision/inference/model/backends/onnx_backend.py
anomavision/inference/model/backends/openvino_backend.py
anomavision/inference/model/backends/tensorrt_backend.py
anomavision/inference/model/backends/torch_backend.py
anomavision/inference/model/backends/torchscript_backend.py
anomavision/inference/model/wrapper.py
anomavision/inference/modelType.py
anomavision/mahalanobis.py
anomavision/padim.py
anomavision/padim_lite.py
anomavision/sampling_methods/__init__.py
anomavision/sampling_methods/kcenter_greedy.py
anomavision/sampling_methods/sampling_def.py
anomavision/test.py
anomavision/utils.py
anomavision/visualization/__init__.py
anomavision/visualization/boundary.py
anomavision/visualization/frame.py
anomavision/visualization/heatmap.py
anomavision/visualization/highlight.py
anomavision/visualization/utils.py
anomavision-3.1.0.dist-info/licenses/LICENSE
anomavision-3.1.0.dist-info/METADATA
anomavision-3.1.0.dist-info/WHEEL
anomavision-3.1.0.dist-info/RECORD
