Metadata-Version: 2.4
Name: anomavision
Version: 3.1.0
Summary: Advanced Anomaly Detection Environment - Deep learning library for state-of-the-art anomaly detection algorithms
License: MIT
License-File: LICENSE
Keywords: anomaly,vision,computer-vision,anomaly-detection,PaDim
Author: Deep Knowledge
Author-email: Deepp.Knowledge@gmail.com
Requires-Python: >=3.10,<3.13
Classifier: License :: OSI Approved :: MIT License
Classifier: Programming Language :: Python :: 3
Classifier: Programming Language :: Python :: 3.10
Classifier: Programming Language :: Python :: 3.11
Classifier: Programming Language :: Python :: 3.12
Provides-Extra: cpu
Provides-Extra: cu118
Provides-Extra: cu121
Provides-Extra: cu124
Provides-Extra: full
Requires-Dist: easydict (==1.13)
Requires-Dist: fastapi (>=0.127.0,<0.128.0)
Requires-Dist: matplotlib (==3.8.3)
Requires-Dist: numpy (==1.26.4)
Requires-Dist: onnx (>=1.15.0,<2.0.0)
Requires-Dist: onnxruntime (>=1.16.0,<1.18) ; extra == "cpu" or extra == "full"
Requires-Dist: onnxruntime-gpu (>=1.16.0) ; extra == "cu118" or extra == "cu121" or extra == "cu124" or extra == "full"
Requires-Dist: opencv-python (>=4.6.0,<5.0.0)
Requires-Dist: openvino-dev (>=2024.0)
Requires-Dist: pydantic (>=2.12.5,<3.0.0)
Requires-Dist: python-multipart (==0.0.20)
Requires-Dist: ruamel-yaml (>=0.18.16,<0.19.0)
Requires-Dist: scikit-image (==0.22.0)
Requires-Dist: scikit-learn (>=1.2,<1.4)
Requires-Dist: streamlit (>=1.52.2,<2.0.0)
Requires-Dist: torch (>=2.4.0) ; extra == "cpu" or extra == "cu118" or extra == "cu121" or extra == "cu124" or extra == "full"
Requires-Dist: torchaudio (>=2.4.0) ; extra == "cpu" or extra == "cu118" or extra == "cu121" or extra == "cu124" or extra == "full"
Requires-Dist: torchvision (>=0.19.0) ; extra == "cpu" or extra == "cu118" or extra == "cu121" or extra == "cu124" or extra == "full"
Requires-Dist: tqdm (>=4.67.1,<5.0.0)
Requires-Dist: uvicorn (>=0.30.0,<0.31.0)
Project-URL: Documentation, https://github.com/DeepKnowledge1/AnomaVision/wiki
Project-URL: Homepage, https://github.com/DeepKnowledge1
Project-URL: Repository, https://github.com/DeepKnowledge1/AnomaVision
